setup.py
wirecloud_pubsub/__init__.py
wirecloud_pubsub/wirecloud.py
wirecloud_pubsub.egg-info/PKG-INFO
wirecloud_pubsub.egg-info/SOURCES.txt
wirecloud_pubsub.egg-info/dependency_links.txt
wirecloud_pubsub.egg-info/requires.txt
wirecloud_pubsub.egg-info/top_level.txt