Metadata-Version: 1.1
Name: wirecloud-pubsub
Version: 0.1
Summary: Wirecloud plugin providing PubSub support.
Home-page: http://github.com/conwetlab/wirecloud-pubsub
Author: CoNWeT Lab
Author-email: wirecloud-pubsub@conwet.com
License: EUPL 1.1
Platform: UNKNOWN
Classifier: Development Status :: 3 - Alpha
Classifier: Environment :: Web Environment
Classifier: Framework :: Django
Classifier: Intended Audience :: Developers
Classifier: License :: OSI Approved :: European Union Public Licence 1.1 (EUPL 1.1)
Classifier: Operating System :: OS Independent
Classifier: Programming Language :: Python
Classifier: Topic :: Software Development :: Libraries :: Python Modules
